README.txt
setup.py
oracler/__init__.py
oracler/__main__.py
oracler/oracler.py
oracler/timer.py
oracler.egg-info/PKG-INFO
oracler.egg-info/SOURCES.txt
oracler.egg-info/dependency_links.txt
oracler.egg-info/requires.txt
oracler.egg-info/top_level.txt